groupdocs/assembly/py.typed
aspose/pycore/py.typed
aspose/pycore/__init__.pyi
aspose/pyreflection/py.typed
aspose/pyreflection/__init__.pyi
aspose/pydrawing/py.typed
aspose/pydrawing/__init__.pyi
aspose/pydrawing/design.pyi
aspose/pydrawing/drawing2d.pyi
aspose/pydrawing/imaging.pyi
aspose/pydrawing/printing.pyi
aspose/pydrawing/text.pyi
groupdocs/assembly/__init__.pyi
groupdocs/assembly/data/__init__.pyi
groupdocs/__init__.py
groupdocs/assembly.cp310-win32.pyd
groupdocs/assembly.cp311-win32.pyd
groupdocs/assembly.cp312-win32.pyd
groupdocs/assembly.cp313-win32.pyd
groupdocs/assembly.cp35-win32.pyd
groupdocs/assembly.cp36-win32.pyd
groupdocs/assembly.cp37-win32.pyd
groupdocs/assembly.cp38-win32.pyd
groupdocs/assembly.cp39-win32.pyd
groupdocs/pycore.cp310-win32.pyd
groupdocs/pycore.cp311-win32.pyd
groupdocs/pycore.cp312-win32.pyd
groupdocs/pycore.cp313-win32.pyd
groupdocs/pycore.cp35-win32.pyd
groupdocs/pycore.cp36-win32.pyd
groupdocs/pycore.cp37-win32.pyd
groupdocs/pycore.cp38-win32.pyd
groupdocs/pycore.cp39-win32.pyd
groupdocs/pygc.cp310-win32.pyd
groupdocs/pygc.cp311-win32.pyd
groupdocs/pygc.cp312-win32.pyd
groupdocs/pygc.cp313-win32.pyd
groupdocs/pygc.cp35-win32.pyd
groupdocs/pygc.cp36-win32.pyd
groupdocs/pygc.cp37-win32.pyd
groupdocs/pygc.cp38-win32.pyd
groupdocs/pygc.cp39-win32.pyd
groupdocs/pyreflection.cp310-win32.pyd
groupdocs/pyreflection.cp311-win32.pyd
groupdocs/pyreflection.cp312-win32.pyd
groupdocs/pyreflection.cp313-win32.pyd
groupdocs/pyreflection.cp35-win32.pyd
groupdocs/pyreflection.cp36-win32.pyd
groupdocs/pyreflection.cp37-win32.pyd
groupdocs/pyreflection.cp38-win32.pyd
groupdocs/pyreflection.cp39-win32.pyd
groupdocs/__pyinstaller/__init__.pyi
groupdocs/__pyinstaller/hook-groupdocs.py
groupdocs/assemblies/assembly/Aspose.Drawing.Common.dll
groupdocs/assemblies/assembly/GroupDocs.Assembly.dll
groupdocs/assemblies/assembly/Microsoft.Win32.SystemEvents.dll
groupdocs/assemblies/assembly/SkiaSharp.dll
groupdocs_assembly_net-25.5.1.dist-info/METADATA
groupdocs_assembly_net-25.5.1.dist-info/WHEEL
groupdocs_assembly_net-25.5.1.dist-info/entry_points.txt
groupdocs_assembly_net-25.5.1.dist-info/top_level.txt
groupdocs_assembly_net-25.5.1.dist-info/RECORD
