Metadata-Version: 2.1
Name: groupdocs-assembly-net
Version: 25.5.1
Summary: GroupDocs.Assembly for Python via .NET solution for automating document creation with advanced data integration.
Home-page: https://products.groupdocs.com/assembly
Author: GroupDocs
License: Other/Proprietary License
Keywords: assembly,file,render,api,pdf,docx,xlsx,pptx,html,png,word,excel,powerpoint,visio,opendocument,photoshop
Platform: win32
Classifier: Operating System :: Microsoft :: Windows
Classifier: Operating System :: POSIX :: Linux
Classifier: Operating System :: Unix
Classifier: License :: Other/Proprietary License
Classifier: Programming Language :: Python :: 3
Classifier: Programming Language :: Python :: 3 :: Only
Classifier: Programming Language :: Python :: 3.8
Classifier: Programming Language :: Python :: 3.9
Classifier: Topic :: Software Development :: Libraries
Classifier: Topic :: Utilities
Requires-Python: >=3.5,<3.14
